MANIFEST.in
README.md
setup.py
django_websocket_channel.egg-info/PKG-INFO
django_websocket_channel.egg-info/SOURCES.txt
django_websocket_channel.egg-info/dependency_links.txt
django_websocket_channel.egg-info/requires.txt
django_websocket_channel.egg-info/top_level.txt
examples/__init__.py
examples/manage.py
examples/settings.py
examples/urls.py
examples/wsgi.py
examples/wsgi_websocket.py
examples/django_websocket/__init__.py
examples/django_websocket/admin.py
examples/django_websocket/models.py
examples/django_websocket/tests.py
examples/django_websocket/views.py
examples/django_websocket/migrations/__init__.py
websocket_channel/__init__.py
websocket_channel/context_processors.py
websocket_channel/django_runserver.py
websocket_channel/exceptions.py
websocket_channel/middleware.py
websocket_channel/publisher.py
websocket_channel/subscriber.py
websocket_channel/uwsgi_runserver.py
websocket_channel/web_socket_message.py
websocket_channel/websocket.py
websocket_channel/websocket_wsgi_server.py
websocket_channel/ws_settings.py
websocket_channel/static/js/dj_websocket.js