Metadata-Version: 1.1
Name: django-websocket-channel
Version: 0.0.5
Summary: Websocket support for Django using Redis
Home-page: https://github.com/neo-hu/django-websocket-channel
Author: Neo hu
Author-email: 9656951@qq.com
License: MIT
Keywords: django,websocket,redis
Platform: UNKNOWN
Classifier: Environment :: Web Environment
Classifier: Framework :: Django
Classifier: Intended Audience :: Developers
Classifier: Programming Language :: Python
Classifier: Topic :: Software Development :: Libraries :: Python Modules
Classifier: Programming Language :: Python :: 2.7
